asflow/__init__.py
asflow/compressor.py
asflow/console.py
asflow/flow.py
asflow/retry.py
asflow/serializer.py
asflow/task.py
asflow-0.0.5.dist-info/METADATA
asflow-0.0.5.dist-info/WHEEL
asflow-0.0.5.dist-info/licenses/LICENSE
asflow-0.0.5.dist-info/RECORD
