Metadata-Version: 2.4
Name: asflow
Version: 0.0.5
Summary: A lightweight, asynchronous workflow runner for ETL pipelines
Project-URL: Documentation, https://asflow.readthedocs.io/en/latest/
Project-URL: Repository, https://github.com/k24d/asflow
License-Expression: MIT
License-File: LICENSE
Classifier: Development Status :: 3 - Alpha
Classifier: Programming Language :: Python :: 3
Classifier: Programming Language :: Python :: 3.11
Classifier: Programming Language :: Python :: 3.12
Classifier: Programming Language :: Python :: 3.13
Requires-Python: >=3.11
Requires-Dist: rich>=14.0.0
